[
{
  "pk": 1, 
  "model": "auth.permission", 
  "fields": {
    "codename": "add_logentry", 
    "name": "Can add log entry", 
    "content_type": 1
  }
},
{
  "pk": 2, 
  "model": "auth.permission", 
  "fields": {
    "codename": "change_logentry", 
    "name": "Can change log entry", 
    "content_type": 1
  }
},
{
  "pk": 3, 
  "model": "auth.permission", 
  "fields": {
    "codename": "delete_logentry", 
    "name": "Can delete log entry", 
    "content_type": 1
  }
},
{
  "pk": 4, 
  "model": "auth.permission", 
  "fields": {
    "codename": "add_permission", 
    "name": "Can add permission", 
    "content_type": 2
  }
},
{
  "pk": 5, 
  "model": "auth.permission", 
  "fields": {
    "codename": "change_permission", 
    "name": "Can change permission", 
    "content_type": 2
  }
},
{
  "pk": 6, 
  "model": "auth.permission", 
  "fields": {
    "codename": "delete_permission", 
    "name": "Can delete permission", 
    "content_type": 2
  }
},
{
  "pk": 7, 
  "model": "auth.permission", 
  "fields": {
    "codename": "add_group", 
    "name": "Can add group", 
    "content_type": 3
  }
},
{
  "pk": 8, 
  "model": "auth.permission", 
  "fields": {
    "codename": "change_group", 
    "name": "Can change group", 
    "content_type": 3
  }
},
{
  "pk": 9, 
  "model": "auth.permission", 
  "fields": {
    "codename": "delete_group", 
    "name": "Can delete group", 
    "content_type": 3
  }
},
{
  "pk": 10, 
  "model": "auth.permission", 
  "fields": {
    "codename": "add_user", 
    "name": "Can add user", 
    "content_type": 4
  }
},
{
  "pk": 11, 
  "model": "auth.permission", 
  "fields": {
    "codename": "change_user", 
    "name": "Can change user", 
    "content_type": 4
  }
},
{
  "pk": 12, 
  "model": "auth.permission", 
  "fields": {
    "codename": "delete_user", 
    "name": "Can delete user", 
    "content_type": 4
  }
},
{
  "pk": 13, 
  "model": "auth.permission", 
  "fields": {
    "codename": "add_contenttype", 
    "name": "Can add content type", 
    "content_type": 5
  }
},
{
  "pk": 14, 
  "model": "auth.permission", 
  "fields": {
    "codename": "change_contenttype", 
    "name": "Can change content type", 
    "content_type": 5
  }
},
{
  "pk": 15, 
  "model": "auth.permission", 
  "fields": {
    "codename": "delete_contenttype", 
    "name": "Can delete content type", 
    "content_type": 5
  }
},
{
  "pk": 16, 
  "model": "auth.permission", 
  "fields": {
    "codename": "add_session", 
    "name": "Can add session", 
    "content_type": 6
  }
},
{
  "pk": 17, 
  "model": "auth.permission", 
  "fields": {
    "codename": "change_session", 
    "name": "Can change session", 
    "content_type": 6
  }
},
{
  "pk": 18, 
  "model": "auth.permission", 
  "fields": {
    "codename": "delete_session", 
    "name": "Can delete session", 
    "content_type": 6
  }
},
{
  "pk": 22, 
  "model": "auth.permission", 
  "fields": {
    "codename": "add_contacts", 
    "name": "Can add contacts", 
    "content_type": 8
  }
},
{
  "pk": 23, 
  "model": "auth.permission", 
  "fields": {
    "codename": "change_contacts", 
    "name": "Can change contacts", 
    "content_type": 8
  }
},
{
  "pk": 24, 
  "model": "auth.permission", 
  "fields": {
    "codename": "delete_contacts", 
    "name": "Can delete contacts", 
    "content_type": 8
  }
},
{
  "pk": 25, 
  "model": "auth.permission", 
  "fields": {
    "codename": "add_myrequest", 
    "name": "Can add my request", 
    "content_type": 9
  }
},
{
  "pk": 26, 
  "model": "auth.permission", 
  "fields": {
    "codename": "change_myrequest", 
    "name": "Can change my request", 
    "content_type": 9
  }
},
{
  "pk": 27, 
  "model": "auth.permission", 
  "fields": {
    "codename": "delete_myrequest", 
    "name": "Can delete my request", 
    "content_type": 9
  }
},
{
  "pk": 2, 
  "model": "auth.user", 
  "fields": {
    "username": "jeyzth", 
    "first_name": "\u0404\u0432\u0433\u0435\u043d", 
    "last_name": "\u0410\u043d\u043e\u043d\u0456\u043c\u043e\u0432", 
    "is_active": true, 
    "is_superuser": true, 
    "is_staff": true, 
    "last_login": "2015-08-15T22:22:04.995Z", 
    "groups": [], 
    "user_permissions": [
      1, 
      2, 
      3, 
      7, 
      8, 
      9, 
      4, 
      5, 
      6, 
      10, 
      11, 
      12, 
      13, 
      14, 
      15, 
      22, 
      23, 
      24, 
      16, 
      17, 
      18
    ], 
    "password": "pbkdf2_sha256$12000$a9TMrKMTZueM$r+0xhAyPJt9I31Q+MQ/d+hXIgTdrR9DWWwimDFCK9hs=", 
    "email": "jeyzth@gmail.com", 
    "date_joined": "2015-08-09T12:39:21Z"
  }
},
{
  "pk": 3, 
  "model": "auth.user", 
  "fields": {
    "username": "admin", 
    "first_name": "Admin", 
    "last_name": "Adminov", 
    "is_active": true, 
    "is_superuser": true, 
    "is_staff": true, 
    "last_login": "2015-08-16T12:32:21.486Z", 
    "groups": [], 
    "user_permissions": [
      1, 
      2, 
      3, 
      7, 
      8, 
      9, 
      4, 
      5, 
      6, 
      10, 
      11, 
      12, 
      13, 
      14, 
      15, 
      22, 
      23, 
      24, 
      16, 
      17, 
      18
    ], 
    "password": "pbkdf2_sha256$12000$Fhsmu5vC5mkK$93G4hUTN3JHK0bH7DTyjDiwYzgA85Oe/Y6IbyKxMuZM=", 
    "email": "", 
    "date_joined": "2015-08-09T12:41:19Z"
  }
}

,
{
    "model": "hello.Contacts",
    "pk": 1,
    "fields": {
        "name":"Євген",
            "surname":"Анонімов",
	    "dateofbird":"1973-03-09",
            "bio":"Працюю у сфері телекомунікацій.\nВикористовую мови програмування:\nС & Shell для написання 'серверних' програм під Linux (x86,armv7)\n    Delphi    для написання 'кліентських' программ під Win32\nPHP + JavaScript для написання 'тонких кліентів' під WEB (LAMP)\nJava вчив колись, але вже не пам'ятаю і не використовую.\nPython вчу зараз, в процесі\n\nЦікавить робота в аутсорсінг фірмі, бажано розробником на Python\nу сфері WEB.",
	    "email":"jeyzth@gmail.com",
	    "jabber":"jeyzth@khavr.com",
	    "skype":"jeyzth",
	    "others":"т. +7(717)123456\nм. +7(707)1234567\nм. +38(050)1234567"
        }
    
    }
    ,
    {
        "model": "hello.MyRequest",
        "pk": 1,
        "fields": {
                  "query_dt":"2015-08-05 00:00:10",
                  "remote_ip":"192.168.88.1",
		  "remote_host":"host-1",
		  "query_string":"http://192.168.88.129"
        }
    }
    ,
    {
        "model": "hello.MyRequest",
        "pk": 2,
        "fields": {
                  "query_dt":"2015-08-05 00:00:10",
                  "remote_ip":"192.168.88.2",
		  "remote_host":"host-2",
		  "query_string":"http://192.168.88.129"
        }
    }
    ,
    {
        "model": "hello.MyRequest",
        "pk": 3,
        "fields": {
                  "query_dt":"2015-08-05 00:00:10",
                  "remote_ip":"192.168.88.3",
		  "remote_host":"host-3",
		  "query_string":"http://192.168.88.129"
        }
    }
    ,
    {
        "model": "hello.MyRequest",
        "pk": 4,
        "fields": {
                  "query_dt":"2015-08-05 00:00:10",
                  "remote_ip":"192.168.88.4",
		  "remote_host":"host-4",
		  "query_string":"http://192.168.88.129"
        }
    }
]
